agenticai/__init__.py
agenticai/api.py
agenticai/config.py
agenticai/generator.py
agenticai/tweetscraper.py
agenticai/utils.py
agentic_core-0.1.1.dist-info/METADATA
agentic_core-0.1.1.dist-info/WHEEL
agentic_core-0.1.1.dist-info/top_level.txt
agentic_core-0.1.1.dist-info/RECORD
