Metadata-Version: 2.2
Name: agentic-core
Version: 0.1.1
Summary: Scrape tweets and generate AI-based tweets.
Author: Your Name
Classifier: Programming Language :: Python :: 3
Classifier: License :: OSI Approved :: MIT License
Classifier: Operating System :: OS Independent
Requires-Python: >=3.6
Requires-Dist: Flask
Requires-Dist: Flask-CORS
Requires-Dist: pyppeteer
Requires-Dist: openai
Requires-Dist: requests
Requires-Dist: python-dotenv
Requires-Dist: nest-asyncio
Requires-Dist: asgiref
Dynamic: author
Dynamic: classifier
Dynamic: description
Dynamic: description-content-type
Dynamic: requires-dist
Dynamic: requires-python
Dynamic: summary
